flm_citations/__init__.py
flm_citations/_cslformatter.py
flm_citations/american-physical-society-et-al--patched.csl
flm_citations/bibtex--patched.csl
flm_citations/citesources/__init__.py
flm_citations/citesources/arxiv.py
flm_citations/citesources/base.py
flm_citations/citesources/bibliographyfile.py
flm_citations/citesources/doi.py
flm_citations/citesources/manual.py
flm_citations/feature.py
flm_citations/flmcitationsscanner.py
flm_citations-0.2.10.dist-info/LICENSE.txt
flm_citations-0.2.10.dist-info/METADATA
flm_citations-0.2.10.dist-info/WHEEL
flm_citations-0.2.10.dist-info/RECORD
