Metadata-Version: 2.1
Name: flm-citations
Version: 0.2.10
Summary: Support for citations in FLM (see flm-core package)
License: MIT
Author: Philippe Faist
Requires-Python: >=3.8,<4.0
Classifier: License :: OSI Approved :: MIT License
Classifier: Programming Language :: Python :: 3
Classifier: Programming Language :: Python :: 3.8
Classifier: Programming Language :: Python :: 3.9
Classifier: Programming Language :: Python :: 3.10
Classifier: Programming Language :: Python :: 3.11
Requires-Dist: PyYAML (>=6.0,<7.0)
Requires-Dist: arxiv (>=1.4.2,<2.0.0)
Requires-Dist: backoff (>=2.1.2,<3.0.0)
Requires-Dist: citeproc-py (>=0.6.0,<0.7.0)
Requires-Dist: flm-core (>=0.3.0a10)
Requires-Dist: requests (>=2.28.1,<3.0.0)
